{
  "temperature": 0.7,
  "humidity": 0.4,
  "precipitation": "rain",
  "downfall": 0.4,
  "effects": {
    "sky_color": 12103935,
    "water_fog_color": 4159204,
    "fog_color": 12103935,
    "water_color": 7906559,
    "grass_color": 9286496,
    "foliage_color": 9286496,
    "mood_sound": {
      "sound": "minecraft:ambient.cave",
      "tick_delay": 6000,
      "block_search_extent": 8,
      "offset": 2.0
    },
    "music": {
      "sound": "minecraft:music.overworld.meadow",
      "min_delay": 12000,
      "max_delay": 24000,
      "replace_current_music": false
    },
    "ambient_sound": "minecraft:ambient.basalt_deltas.loop"
  },
  "spawners": {
    "monster": [
      {
        "type": "minecraft:phantom",
        "weight": 5,
        "minCount": 1,
        "maxCount": 2
      }
    ],
    "creature": [
      {
        "type": "minecraft:bat",
        "weight": 10,
        "minCount": 8,
        "maxCount": 8
      },
      {
        "type": "minecraft:parrot",
        "weight": 8,
        "minCount": 1,
        "maxCount": 2
      }
    ],
    "ambient": [
      {
        "type": "minecraft:bat",
        "weight": 10,
        "minCount": 8,
        "maxCount": 8
      }
    ],
    "water_creature": [],
    "water_ambient": [],
    "misc": []
  },
  "spawn_costs": {},
  "carvers": {
    "air": []
  },
  "features": [
    [],
    [],
    [],
    [
      "dimensionsmod:aether_island_base"
    ],
    [
      "dimensionsmod:aether_cloud_patches"
    ],
    [],
    [
      "dimensionsmod:aether_trees"
    ],
    [
      "dimensionsmod:aether_grass"
    ],
    [],
    [
      "dimensionsmod:aether_crystals",
      "dimensionsmod:aether_ore_generation"
    ]
  ]
} 